pyo3_antelope_rs-1.3.0.dist-info/METADATA
pyo3_antelope_rs-1.3.0.dist-info/WHEEL
antelope_rs/__init__.py
antelope_rs/abi.py
antelope_rs/codec.py
antelope_rs/testing.py
antelope_rs/_lowlevel.abi3.so
pyo3_antelope_rs-1.3.0.dist-info/RECORD
