Metadata-Version: 2.4
Name: pyo3-antelope-rs
Version: 1.3.0
Requires-Dist: frozendict>=2.4.6
Requires-Dist: maturin>=1.8.2
Requires-Dist: msgspec>=0.19.0
Summary: PyO3 bindings to telosnetwork/antelope-rs + some QoL addons
Author-email: Guillermo Rodriguez <guillermo@telos.net>
Requires-Python: >=3.9
